pwnit/args.py
pwnit/binary.py
pwnit/commands.py
pwnit/config.py
pwnit/exe.py
pwnit/file_manage.py
pwnit/interactions.py
pwnit/libc.py
pwnit/main.py
pwnit/placeholders.py
pwnit/template.py
pwnit/utils.py
pwnit/resources/config.schema.json
pwnit/resources/config.yml
pwnit/resources/template.py
pwnit-0.7.7.dist-info/METADATA
pwnit-0.7.7.dist-info/WHEEL
pwnit-0.7.7.dist-info/entry_points.txt
pwnit-0.7.7.dist-info/licenses/LICENSE
pwnit-0.7.7.dist-info/RECORD
