Metadata-Version: 2.4
Name: pwnit
Version: 0.7.7
Summary: Automatic tool to quickly start a pwn CTF challenge
Project-URL: Homepage, https://github.com/Church-17/pwnit
Author-email: Matteo Chiesa <matteo.chiesa.mc@gmail.com>
Maintainer-email: Matteo Chiesa <matteo.chiesa.mc@gmail.com>
License: MIT License
License-File: LICENSE
Keywords: ctf,pwn
Classifier: Development Status :: 4 - Beta
Classifier: Environment :: Console
Classifier: Intended Audience :: Developers
Classifier: License :: OSI Approved :: MIT License
Classifier: Operating System :: POSIX :: Linux
Classifier: Programming Language :: Python
Classifier: Programming Language :: Python :: 3
Requires-Python: >=3.10
Requires-Dist: jsonschema
Requires-Dist: pwntools
Requires-Dist: pyyaml
Requires-Dist: requests
Requires-Dist: yara-python
